AUTHORS.rst
CONTRIBUTING.rst
HISTORY.rst
LICENSE
MANIFEST.in
README.rst
setup.py
mts/__init__.py
mts/cli.py
mts/db.sqlite3
mts/manage.py
mts/settings.py
mts.egg-info/PKG-INFO
mts.egg-info/SOURCES.txt
mts.egg-info/dependency_links.txt
mts.egg-info/entry_points.txt
mts.egg-info/not-zip-safe
mts.egg-info/requires.txt
mts.egg-info/top_level.txt
mts/orm_magic/__init__.py
mts/orm_magic/hosts.py
mts/orm_magic/models.py