Metadata-Version: 1.1
Name: mts
Version: 0.3
Summary: Miratuserie.tv on the command line
Home-page: https://github.com/mgaitan/mts
Author: Martín Gaitán
Author-email: gaitan@gmail.com
License: BSD
Keywords: mts
Platform: UNKNOWN
Classifier: Development Status :: 2 - Pre-Alpha
Classifier: Intended Audience :: Developers
Classifier: License :: OSI Approved :: BSD License
Classifier: Natural Language :: English
Classifier: Programming Language :: Python :: 2
Classifier: Programming Language :: Python :: 2.6
Classifier: Programming Language :: Python :: 2.7
Classifier: Programming Language :: Python :: 3
Classifier: Programming Language :: Python :: 3.3
